kedex/__init__.py
kedex/context/__init__.py
kedex/context/catalog_sugar_context.py
kedex/context/flexible_context.py
kedex/context/keep_output_context.py
kedex/context/mlflow_context.py
kedex/context/only_missing_string_runner_context.py
kedex/context/pipelines_in_parameters_context.py
kedex/decorators/__init__.py
kedex/decorators/decorators.py
kedex/decorators/pandas_decorators.py
kedex/hatch_dict/__init__.py
kedex/hatch_dict/hatch_dict.py
kedex/io/__init__.py
kedex/io/pandas/__init__.py
kedex/io/pandas/efficient_csv_local.py
kedex/io/pandas/pandas_cat_matrix.py
kedex/io/pandas/pandas_describe.py
kedex/io/pandas_profiling/__init__.py
kedex/io/pandas_profiling/pandas_profiling.py
kedex/io/pillow/__init__.py
kedex/io/pillow/images.py
kedex/io/seaborn/__init__.py
kedex/io/seaborn/seaborn_pairplot.py
kedex/io/torchvision/__init__.py
kedex/io/torchvision/iterable_images.py
kedex/ops/__init__.py
kedex/ops/allennlp_ops.py
kedex/ops/argparse_ops.py
kedex/ops/pandas_ops.py
kedex/ops/pytorch_ops.py
kedex/ops/shap_ops.py
kedex/ops/sklearn_ops.py
kedex/ops/ignite/__init__.py
kedex/ops/ignite/contrib/__init__.py
kedex/ops/ignite/contrib/handlers/__init__.py
kedex/ops/ignite/contrib/handlers/base_logger.py
kedex/ops/ignite/contrib/handlers/mlflow_logger.py
kedex/pipeline/__init__.py
kedex/pipeline/pipeline.py
kedex/pipeline/sub_pipeline.py
kedex-0.1.0.dist-info/LICENSE
kedex-0.1.0.dist-info/METADATA
kedex-0.1.0.dist-info/WHEEL
kedex-0.1.0.dist-info/top_level.txt
kedex-0.1.0.dist-info/RECORD
