Metadata-Version: 2.1
Name: kedex
Version: 0.1.0
Summary: Kedro extension for rapid prototyping and experimentation
Home-page: https://github.com/Minyus/kedex
Author: Yusuke Minami
Author-email: me@minyus.github.com
License: Apache Software License (Apache 2.0)
Keywords: pipelines,machine learning,data pipelines,data science,data engineering
Platform: UNKNOWN
Classifier: Development Status :: 3 - Alpha
Classifier: Natural Language :: English
Classifier: Programming Language :: Python :: 3.5
Classifier: Programming Language :: Python :: 3.6
Classifier: Programming Language :: Python :: 3.7
Classifier: Operating System :: OS Independent
Requires-Dist: six
